aider/__init__.py
aider/__main__.py
aider/analytics.py
aider/args.py
aider/args_formatter.py
aider/coders/__init__.py
aider/coders/architect_coder.py
aider/coders/architect_prompts.py
aider/coders/ask_coder.py
aider/coders/ask_prompts.py
aider/coders/base_coder.py
aider/coders/base_prompts.py
aider/coders/chat_chunks.py
aider/coders/editblock_coder.py
aider/coders/editblock_fenced_coder.py
aider/coders/editblock_fenced_prompts.py
aider/coders/editblock_func_coder.py
aider/coders/editblock_func_prompts.py
aider/coders/editblock_prompts.py
aider/coders/editor_editblock_coder.py
aider/coders/editor_editblock_prompts.py
aider/coders/editor_whole_coder.py
aider/coders/editor_whole_prompts.py
aider/coders/help_coder.py
aider/coders/help_prompts.py
aider/coders/search_replace.py
aider/coders/single_wholefile_func_coder.py
aider/coders/single_wholefile_func_prompts.py
aider/coders/udiff_coder.py
aider/coders/udiff_prompts.py
aider/coders/wholefile_coder.py
aider/coders/wholefile_func_coder.py
aider/coders/wholefile_func_prompts.py
aider/coders/wholefile_prompts.py
aider/commands.py
aider/copypaste.py
aider/diffs.py
aider/dump.py
aider/editor.py
aider/exceptions.py
aider/format_settings.py
aider/gui.py
aider/help.py
aider/help_pats.py
aider/history.py
aider/io.py
aider/linter.py
aider/llm.py
aider/main.py
aider/mdstream.py
aider/models.py
aider/prompts.py
aider/queries/tree-sitter-language-pack/csharp-tags.scm
aider/queries/tree-sitter-language-pack/javascript-tags.scm
aider/queries/tree-sitter-languages/README.md
aider/queries/tree-sitter-languages/c-tags.scm
aider/queries/tree-sitter-languages/c_sharp-tags.scm
aider/queries/tree-sitter-languages/cpp-tags.scm
aider/queries/tree-sitter-languages/dart-tags.scm
aider/queries/tree-sitter-languages/elisp-tags.scm
aider/queries/tree-sitter-languages/elixir-tags.scm
aider/queries/tree-sitter-languages/elm-tags.scm
aider/queries/tree-sitter-languages/go-tags.scm
aider/queries/tree-sitter-languages/hcl-tags.scm
credor_chat-0.0.2.dist-info/LICENSE.txt
credor_chat-0.0.2.dist-info/METADATA
credor_chat-0.0.2.dist-info/WHEEL
credor_chat-0.0.2.dist-info/entry_points.txt
credor_chat-0.0.2.dist-info/RECORD
